<?xml version="1.0" encoding="UTF-8"?>
<brands>
	<brand name="AGCO" text="AGCO" />
	<brand name="AGRISEM" text="AGRISEM" />
	<brand name="AGROMASZ" text="AGRO-MASZ" />
	<brand name="AMAZONE" text="AMAZONE" />
	<brand name="ANNABURGER" text="ANNABURGER" />
	<brand name="ARCUSIN" text="arcusin" />
	<brand name="ARMATRAC" text="ArmaTrac" />
	<brand name="BEDNAR" text="BEDNAR" />
	<brand name="BERGMANN" text="BERGMANN" />
	<brand name="BOECKMANN" text="BOECKMANN" />
	<brand name="BREDAL" text="BREDAL" />
	<brand name="CAPELLO" text="capello" />
	<brand name="CASEIH" text="Case IH" />
	<brand name="CHALLENGER" text="Challenger" />
	<brand name="DAMCON" text="Damcon" />
	<brand name="DEUTZFAHR" text="Deutz-Fahr" />
	<brand name="DFM" text="DFM" />
	<brand name="DUEVELSDORF" text="DUEVELSDORF" />
	<brand name="EINBOECK" text="EINBOECK" />
	<brand name="ELMERSMFG" text="ELMERSMFG" />
	<brand name="FARMTECH" text="FARMTECH" />
	<brand name="FENDT" text="FENDT" />
	<brand name="FIAT" text="FIAT" />
	<brand name="FLEXICOIL" text="FLEXICOIL" />
	<brand name="FLIEGL" text="FLIEGL" />
	<brand name="FMZ" text="FMZ" />
	<brand name="FORTSCHRITT" text="FORTSCHRITT" />
	<brand name="FSI" text="FSI" />
	<brand name="GESSNER" text="GESSNER" />
	<brand name="GOLDHOFER" text="GOLDHOFER" />
	<brand name="GREATPLAINS" text="GREATPLAINS" />
	<brand name="GREGOIREBESSON" text="GREGOIREBESSON" />
	<brand name="GRIMME" text="GRIMME" />
	<brand name="HARDI" text="HARDI" />
	<brand name="HATZENBICHLER" text="HATZENBICHLER" />
	<brand name="HOLARAS" text="HOLARAS" />
	<brand name="HOLMER" text="HOLMER" />
	<brand name="HORSCH" text="HORSCH" />
	<brand name="JCB" text="JCB" />
	<brand name="JENZ" text="JENZ" />
	<brand name="JOHNDEERE" text="JOHNDEERE" />
	<brand name="JOSKIN" text="JOSKIN" />
	<brand name="KEMPER" text="KEMPER" />
	<brand name="KINZE" text="KINZE" />
	<brand name="KOMATSU" text="KOMATSU" />
	<brand name="KOTTE" text="KOTTE" />
	<brand name="KRAMER" text="KRAMER" />
	<brand name="KRAMPE" text="KRAMPE" />
	<brand name="KROEGER" text="KROEGER" />
	<brand name="KRONE" text="KRONE" />
	<brand name="KUHN" text="KUHN" />
	<brand name="KVERNELAND" text="KVERNELAND" />
	<brand name="LELY" text="LELY" />
	<brand name="LEMKEN" text="LEMKEN" />
	<brand name="LINDNER" text="LINDNER" />
	<brand name="LIZARD" text="LIZARD" />
	<brand name="LODEKING" text="LODEKING" />
	<brand name="MAGSI" text="MAGSI" />
	<brand name="MAN" text="MAN" />
	<brand name="MANITOU" text="MANITOU" />
	<brand name="MASSEYFERGUSON" text="MASSEYFERGUSON" />
	<brand name="MICHIELETTO" text="MICHIELETTO" />
	<brand name="NEWHOLLAND" text="NEWHOLLAND" />
	<brand name="PALADIN" text="PALADIN" />
	<brand name="POETTINGER" text="POETTINGER" />
	<brand name="PONSSE" text="PONSSE" />
	<brand name="RABE" text="RABE" />
	<brand name="RANDON" text="RANDON" />
	<brand name="RAU" text="RAU" />
	<brand name="ROPA" text="ROPA" />
	<brand name="ROSTSELMASH" text="ROSTSELMASH" />
	<brand name="SALFORD" text="SALFORD" />
	<brand name="SAMPOROSENLEW" text="SAMPOROSENLEW" />
	<brand name="SAMSONAGRO" text="SAMSONAGRO" />
	<brand name="SCHUITEMAKER" text="SCHUITEMAKER" />
	<brand name="SILOKING" text="SILOKING" />
	<brand name="STARA" text="STARA" />
	<brand name="STEPA" text="STEPA" />
	<brand name="STEYR" text="STEYR" />
	<brand name="STOLL" text="STOLL" />
	<brand name="STRAUTMANN" text="STRAUTMANN" />
	<brand name="SUER" text="SUER" />
	<brand name="TATRA" text="TATRA" />
	<brand name="THUERINGERAGRAR" text="THUERINGERAGRAR" />
	<brand name="THUNDERCREEK" text="THUNDERCREEK" />
	<brand name="TREFFLER" text="TREFFLER" />
	<brand name="TT" text="TT" />
	<brand name="UNVERFERTH" text="UNVERFERTH" />
	<brand name="VAEDERSTAD" text="VAEDERSTAD" />
	<brand name="VALTRA" text="VALTRA" />
	<brand name="VEENHUIS" text="VEENHUIS" />
	<brand name="VICON" text="VICON" />
	<brand name="WARZEE" text="WARZEE" />
	<brand name="WILSON" text="WILSON" />
	<brand name="ZIEGLER" text="ZIEGLER" />
	<brand name="ZUNHAMMER" text="ZUNHAMMER" />
</brands>
